Metadata-Version: 1.1
Name: prepro
Version: 0.5
Summary: Useful for Auto Pre-processing
Home-page: https://github.com/stsfaroz/prepro
Author: SALMAN_FAROZ
Author-email: farozsts@gmail.com
License: MIT
Download-URL: https://github.com/stsfaroz/prepro/archive/0.1.tar.gz
Keywords: missing values,preprocessig
Platform: UNKNOWN
Classifier: Development Status :: 4 - Beta
Classifier: Intended Audience :: Developers
Classifier: Topic :: Software Development :: Build Tools
Classifier: License :: OSI Approved :: MIT License
Classifier: Programming Language :: Python :: 3.6
